odoo9_addon_stock_picking_show_backorder-9.0.1.0.0-py2.7-nspkg.pth
odoo9_addon_stock_picking_show_backorder-9.0.1.0.0.dist-info/DESCRIPTION.rst
odoo9_addon_stock_picking_show_backorder-9.0.1.0.0.dist-info/METADATA
odoo9_addon_stock_picking_show_backorder-9.0.1.0.0.dist-info/RECORD
odoo9_addon_stock_picking_show_backorder-9.0.1.0.0.dist-info/WHEEL
odoo9_addon_stock_picking_show_backorder-9.0.1.0.0.dist-info/metadata.json
odoo9_addon_stock_picking_show_backorder-9.0.1.0.0.dist-info/namespace_packages.txt
odoo9_addon_stock_picking_show_backorder-9.0.1.0.0.dist-info/top_level.txt
odoo_addons/stock_picking_show_backorder/README.rst
odoo_addons/stock_picking_show_backorder/__init__.py
odoo_addons/stock_picking_show_backorder/__openerp__.py
odoo_addons/stock_picking_show_backorder/models/__init__.py
odoo_addons/stock_picking_show_backorder/models/stock.py
odoo_addons/stock_picking_show_backorder/views/stock_view.xml
